{
  "swagger": "2.0",
  "info": {
    "title": "Sifa Tugas Akhir REST API",
    "description": "private REST API for sifa tugas akhir",
    "contact": {
      "name": "NPE Digital",
      "url": "http://npedigihouse.tech",
      "email": "npedigital@gmail.com"
    },
    "version": "3.0.3"
  },
  "host": "localhost:8080",
  "basePath": "/",
  "schemes": ["http"],
  "paths": {
    "/api/v0/users/": {
      "post": {
        "tags": ["users"],
        "description": "",
        "parameters": [
          {
            "name": "authorization",
            "in": "header",
            "type": "string"
          },
          {
            "name": "body",
            "in": "body",
            "schema": {
              "type": "object",
              "properties": {
                "email": {
                  "example": "any"
                },
                "name": {
                  "example": "any"
                },
                "username": {
                  "example": "any"
                },
                "groupAccess": {
                  "example": "any"
                }
              }
            }
          }
        ],
        "responses": {
          "201": {
            "description": "Created"
          }
        }
      }
    },
    "/api/v0/users/students": {
      "get": {
        "tags": ["users"],
        "description": "",
        "parameters": [
          {
            "name": "authorization",
            "in": "header",
            "type": "string"
          },
          {
            "name": "page",
            "in": "query",
            "type": "string"
          },
          {
            "name": "limit",
            "in": "query",
            "type": "string"
          }
        ],
        "responses": {
          "200": {
            "description": "OK"
          }
        }
      }
    },
    "/api/v0/users/login": {
      "post": {
        "tags": ["users"],
        "description": "",
        "parameters": [
          {
            "name": "authorization",
            "in": "header",
            "type": "string"
          }
        ],
        "responses": {
          "200": {
            "description": "OK"
          }
        }
      }
    },
    "/api/v0/users/{username}/forget-password": {
      "get": {
        "tags": ["users"],
        "description": "",
        "parameters": [
          {
            "name": "username",
            "in": "path",
            "required": true,
            "type": "string"
          },
          {
            "name": "authorization",
            "in": "header",
            "type": "string"
          }
        ],
        "responses": {
          "200": {
            "description": "OK"
          }
        }
      }
    },
    "/api/v0/users/{username}/reset-password/{token}": {
      "post": {
        "tags": ["users"],
        "description": "",
        "parameters": [
          {
            "name": "username",
            "in": "path",
            "required": true,
            "type": "string"
          },
          {
            "name": "token",
            "in": "path",
            "required": true,
            "type": "string"
          },
          {
            "name": "authorization",
            "in": "header",
            "type": "string"
          },
          {
            "name": "body",
            "in": "body",
            "schema": {
              "type": "object",
              "properties": {
                "password": {
                  "example": "any"
                }
              }
            }
          }
        ],
        "responses": {
          "200": {
            "description": "OK"
          }
        }
      }
    },
    "/api/v0/students/{nim}": {
      "get": {
        "tags": ["students"],
        "description": "",
        "parameters": [
          {
            "name": "nim",
            "in": "path",
            "required": true,
            "type": "string"
          },
          {
            "name": "authorization",
            "in": "header",
            "type": "string"
          }
        ],
        "responses": {
          "200": {
            "description": "OK"
          }
        }
      },
      "put": {
        "tags": ["students"],
        "description": "",
        "parameters": [
          {
            "name": "nim",
            "in": "path",
            "required": true,
            "type": "string"
          },
          {
            "name": "authorization",
            "in": "header",
            "type": "string"
          },
          {
            "name": "body",
            "in": "body",
            "schema": {
              "type": "object",
              "properties": {
                "birthDate": {
                  "example": "any"
                }
              }
            }
          }
        ],
        "responses": {
          "200": {
            "description": "OK"
          }
        }
      }
    },
    "/api/v0/students/{nim}/reqlabs": {
      "get": {
        "tags": ["students"],
        "description": "",
        "parameters": [
          {
            "name": "nim",
            "in": "path",
            "required": true,
            "type": "string"
          },
          {
            "name": "authorization",
            "in": "header",
            "type": "string"
          }
        ],
        "responses": {
          "200": {
            "description": "OK"
          }
        }
      },
      "post": {
        "tags": ["students"],
        "description": "",
        "parameters": [
          {
            "name": "nim",
            "in": "path",
            "required": true,
            "type": "string"
          },
          {
            "name": "authorization",
            "in": "header",
            "type": "string"
          },
          {
            "name": "body",
            "in": "body",
            "schema": {
              "type": "object",
              "properties": {
                "labID": {
                  "example": "any"
                },
                "studentNIM": {
                  "example": "any"
                }
              }
            }
          }
        ],
        "responses": {
          "201": {
            "description": "Created"
          }
        }
      }
    },
    "/api/v0/students/{nim}/reqlabs/{reqlabsID}": {
      "put": {
        "tags": ["students"],
        "description": "",
        "parameters": [
          {
            "name": "nim",
            "in": "path",
            "required": true,
            "type": "string"
          },
          {
            "name": "reqlabsID",
            "in": "path",
            "required": true,
            "type": "string"
          },
          {
            "name": "authorization",
            "in": "header",
            "type": "string"
          },
          {
            "name": "body",
            "in": "body",
            "schema": {
              "type": "object",
              "properties": {
                "labID": {
                  "example": "any"
                }
              }
            }
          }
        ],
        "responses": {
          "200": {
            "description": "OK"
          }
        }
      },
      "delete": {
        "tags": ["students"],
        "description": "",
        "parameters": [
          {
            "name": "nim",
            "in": "path",
            "required": true,
            "type": "string"
          },
          {
            "name": "reqlabsID",
            "in": "path",
            "required": true,
            "type": "string"
          },
          {
            "name": "authorization",
            "in": "header",
            "type": "string"
          }
        ],
        "responses": {
          "200": {
            "description": "OK"
          }
        }
      }
    },
    "/api/v0/students/{nim}/thesis": {
      "get": {
        "tags": ["students"],
        "description": "",
        "parameters": [
          {
            "name": "nim",
            "in": "path",
            "required": true,
            "type": "string"
          },
          {
            "name": "authorization",
            "in": "header",
            "type": "string"
          },
          {
            "name": "excludeProposalStatus",
            "in": "query",
            "type": "string"
          }
        ],
        "responses": {
          "200": {
            "description": "OK"
          }
        }
      },
      "post": {
        "tags": ["students"],
        "description": "",
        "parameters": [
          {
            "name": "nim",
            "in": "path",
            "required": true,
            "type": "string"
          },
          {
            "name": "authorization",
            "in": "header",
            "type": "string"
          },
          {
            "name": "body",
            "in": "body",
            "schema": {
              "type": "object",
              "properties": {
                "title_1st": {
                  "example": "any"
                },
                "title_2nd": {
                  "example": "any"
                },
                "labID_1st": {
                  "example": "any"
                },
                "labID2_1st": {
                  "example": "any"
                },
                "lecturerPropose_1st": {
                  "example": "any"
                },
                "labID_2nd": {
                  "example": "any"
                },
                "labID2_2nd": {
                  "example": "any"
                },
                "lecturerPropose_2nd": {
                  "example": "any"
                }
              }
            }
          }
        ],
        "responses": {
          "201": {
            "description": "Created"
          }
        }
      }
    },
    "/api/v0/students/{nim}/thesis/{proposalGroupID}": {
      "put": {
        "tags": ["students"],
        "description": "",
        "parameters": [
          {
            "name": "nim",
            "in": "path",
            "required": true,
            "type": "string"
          },
          {
            "name": "proposalGroupID",
            "in": "path",
            "required": true,
            "type": "string"
          },
          {
            "name": "authorization",
            "in": "header",
            "type": "string"
          },
          {
            "name": "body",
            "in": "body",
            "schema": {
              "type": "object",
              "properties": {
                "title_1st": {
                  "example": "any"
                },
                "title_2nd": {
                  "example": "any"
                }
              }
            }
          }
        ],
        "responses": {
          "201": {
            "description": "Created"
          }
        }
      },
      "delete": {
        "tags": ["students"],
        "description": "",
        "parameters": [
          {
            "name": "nim",
            "in": "path",
            "required": true,
            "type": "string"
          },
          {
            "name": "proposalGroupID",
            "in": "path",
            "required": true,
            "type": "string"
          },
          {
            "name": "authorization",
            "in": "header",
            "type": "string"
          }
        ],
        "responses": {
          "200": {
            "description": "OK"
          }
        }
      }
    },
    "/api/v0/group-units/": {
      "get": {
        "tags": ["group-units"],
        "description": "",
        "parameters": [
          {
            "name": "authorization",
            "in": "header",
            "type": "string"
          },
          {
            "name": "groupID",
            "in": "query",
            "type": "string"
          }
        ],
        "responses": {
          "200": {
            "description": "OK"
          }
        }
      },
      "post": {
        "tags": ["group-units"],
        "description": "",
        "parameters": [
          {
            "name": "authorization",
            "in": "header",
            "type": "string"
          },
          {
            "name": "body",
            "in": "body",
            "schema": {
              "type": "object",
              "properties": {
                "accessName": {
                  "example": "any"
                },
                "groupID": {
                  "example": "any"
                }
              }
            }
          }
        ],
        "responses": {
          "201": {
            "description": "Created"
          }
        }
      }
    },
    "/api/v0/groups/": {
      "get": {
        "tags": ["groups"],
        "description": "",
        "parameters": [
          {
            "name": "authorization",
            "in": "header",
            "type": "string"
          },
          {
            "name": "groupID",
            "in": "query",
            "type": "string"
          }
        ],
        "responses": {
          "200": {
            "description": "OK"
          }
        }
      }
    },
    "/api/v0/lecturers/": {
      "post": {
        "tags": ["lecturers"],
        "description": "",
        "parameters": [
          {
            "name": "authorization",
            "in": "header",
            "type": "string"
          },
          {
            "name": "body",
            "in": "body",
            "schema": {
              "type": "object",
              "properties": {
                "name": {
                  "example": "any"
                },
                "nip": {
                  "example": "any"
                },
                "departmentID": {
                  "example": "any"
                }
              }
            }
          }
        ],
        "responses": {
          "201": {
            "description": "Created"
          }
        }
      },
      "get": {
        "tags": ["lecturers"],
        "description": "",
        "parameters": [
          {
            "name": "authorization",
            "in": "header",
            "type": "string"
          },
          {
            "name": "departmentID",
            "in": "query",
            "type": "string"
          }
        ],
        "responses": {
          "200": {
            "description": "OK"
          }
        }
      }
    },
    "/api/v0/lecturers/{nim}": {
      "get": {
        "tags": ["lecturers"],
        "description": "",
        "parameters": [
          {
            "name": "nim",
            "in": "path",
            "required": true,
            "type": "string"
          },
          {
            "name": "authorization",
            "in": "header",
            "type": "string"
          }
        ],
        "responses": {
          "200": {
            "description": "OK"
          }
        }
      }
    },
    "/api/v0/departments/": {
      "get": {
        "tags": ["departments"],
        "description": "",
        "parameters": [
          {
            "name": "authorization",
            "in": "header",
            "type": "string"
          }
        ],
        "responses": {
          "200": {
            "description": "OK"
          }
        }
      }
    },
    "/api/v0/vocations/{departmentID}": {
      "get": {
        "tags": ["vocations"],
        "description": "",
        "parameters": [
          {
            "name": "departmentID",
            "in": "path",
            "required": true,
            "type": "string"
          },
          {
            "name": "authorization",
            "in": "header",
            "type": "string"
          }
        ],
        "responses": {
          "200": {
            "description": "OK"
          }
        }
      }
    },
    "/api/v0/laboratories/": {
      "get": {
        "tags": ["laboratories"],
        "description": "",
        "parameters": [
          {
            "name": "authorization",
            "in": "header",
            "type": "string"
          }
        ],
        "responses": {
          "200": {
            "description": "OK"
          }
        }
      }
    }
  }
}
